{
  "inpiration": [
    {
      "quote": "I love deadlines. I love the whooshing noise they make as they go by.",
      "author": "Douglas Adams"
    },
    {
      "quote": "There is no greater agony than bearing an untold story inside you.",
      "author": "Maya Angelou"
    },
    {
      "quote": "What really knocks me out is a book that, when you're all done reading it, you wish the author that wrote it was a terrific friend of yours and you could call him up on the phone whenever you felt like it. That doesn't happen much, though.",
      "author": "J.D. Salinger"
    },
    {
      "quote": "We write to taste life twice, in the moment and in retrospect.",
      "author": "Anais Nin"
    },
    {
      "quote": "One day I will find the right words, and they will be simple.",
      "author": "Jack Kerouac"
    },
    {
      "quote": "Fantasy is hardly an escape from reality. It's a way of understanding it",
      "author": "Lloyd Alexander"
    },
    {
      "quote": "And by the way, everything in life is writable about if you have the outgoing guts to do it, and the imagination to improvise. The worst enemy to creativity is self-doubt.",
      "author": "Sylvia Plath"
    },
    {
      "quote": "You never have to change anything you got up in the middle of the night to write.",
      "author": "Saul Bellow"
    }
  ]
}
